src/__init__.py
segmenter-0.0.0.dist-info/METADATA
segmenter-0.0.0.dist-info/WHEEL
segmenter-0.0.0.dist-info/licenses/LICENSE
segmenter-0.0.0.dist-info/RECORD
