Metadata-Version: 2.3
Name: segmenter
Version: 0.0.0
Summary: A segmented display tool for Python!
Project-URL: Documentation, https://segmenter.rtfd.io
Project-URL: Homepage, https://pigeon.uk.to/segmenter
Project-URL: Issues / Bugs, https://github.com/thatgaypigeon/segmenter/issues
Project-URL: PyPI, https://pypi.org/project/segmenter
Project-URL: Support Server, https://discord.gg/aB4Bw5pyTS
Project-URL: Wikipedia Page, https://en.wikipedia.org/wiki/Display_device#Segment_displays
Author-email: thatgaypigeon <pigeon43.stuff@gmail.com>
License: The MIT License (MIT)
License-File: LICENSE
Keywords: 14-segment display,16-segment display,7-segment display,8-segment display,9-segment display,FSD,SISD,SSD,display,recurrence relation,segment,segmented,segmented display,segmented displays,segments
Classifier: Development Status :: 1 - Planning
Classifier: Intended Audience :: Developers
Classifier: License :: OSI Approved
Classifier: License :: OSI Approved :: MIT License
Classifier: Natural Language :: English
Classifier: Operating System :: OS Independent
Classifier: Programming Language :: Python
Classifier: Programming Language :: Python :: 3.8
Classifier: Programming Language :: Python :: 3.9
Classifier: Programming Language :: Python :: 3.10
Classifier: Programming Language :: Python :: 3.11
Classifier: Programming Language :: Python :: 3.12
Classifier: Topic :: Multimedia
Classifier: Topic :: Multimedia :: Graphics
Classifier: Topic :: Other/Nonlisted Topic
Classifier: Topic :: Scientific/Engineering
Classifier: Topic :: Software Development
Classifier: Topic :: Software Development :: Libraries
Classifier: Topic :: Software Development :: Libraries :: Python Modules
Classifier: Typing :: Typed
Requires-Python: >=3.8
